LICENSE
README.md
setup.py
src/remote_mole.egg-info/PKG-INFO
src/remote_mole.egg-info/SOURCES.txt
src/remote_mole.egg-info/dependency_links.txt
src/remote_mole.egg-info/entry_points.txt
src/remote_mole.egg-info/requires.txt
src/remote_mole.egg-info/top_level.txt
src/remote_mole/_internal/__init__.py
src/remote_mole/_internal/platforms/__init__.py
src/remote_mole/_internal/platforms/discord/__init__.py
src/remote_mole/_internal/platforms/discord/daemon.py
src/remote_mole/_internal/services/__init__.py
src/remote_mole/_internal/services/lxi.py
src/remote_mole/_internal/services/ngrok.py
src/remote_mole/setup/__init__.py
src/remote_mole/setup/entrypoint.py