Metadata-Version: 2.1
Name: remote-mole
Version: 1.4.1
Summary: Create moles on remote setups.
Home-page: http://packages.python.org/remote_mole
Author: ACESRG
Author-email: aces.rg@gmail.com
License: GPLv3
Keywords: bots ssh jupyter ngrok discord
Platform: UNKNOWN
License-File: LICENSE
